ietfparse/__init__.py
ietfparse/_helpers.py
ietfparse/algorithms.py
ietfparse/datastructures.py
ietfparse/errors.py
ietfparse/headers.py
ietfparse/py.typed
ietfparse-1.9.0.dist-info/AUTHORS.rst
ietfparse-1.9.0.dist-info/LICENSE
ietfparse-1.9.0.dist-info/METADATA
ietfparse-1.9.0.dist-info/WHEEL
ietfparse-1.9.0.dist-info/top_level.txt
ietfparse-1.9.0.dist-info/RECORD
