Metadata-Version: 2.1
Name: ietfparse
Version: 1.9.0
Summary: Parse formats defined in IETF RFCs
Home-page: https://github.com/dave-shawley/ietfparse
Author: Dave Shawley
Author-email: daveshawley@gmail.com
License: BSD
Project-URL: Documentation, https://ietfparse.readthedocs.io/
Project-URL: Source Code, https://github.com/dave-shawley/ietfparse
Project-URL: Code Coverage, https://coveralls.io/github/dave-shawley/ietfparse
Project-URL: Maintainability, https://codeclimate.com/github/dave-shawley/ietfparse/
Platform: any
Classifier: Intended Audience :: Developers
Classifier: License :: OSI Approved :: BSD License
Classifier: Operating System :: OS Independent
Classifier: Programming Language :: Python
Classifier: Programming Language :: Python :: 3
Classifier: Programming Language :: Python :: 3.7
Classifier: Programming Language :: Python :: 3.8
Classifier: Programming Language :: Python :: 3.9
Classifier: Programming Language :: Python :: 3.10
Classifier: Development Status :: 5 - Production/Stable
Classifier: Environment :: Web Environment
Classifier: Topic :: Internet :: WWW/HTTP
Classifier: Topic :: Text Processing
Classifier: Typing :: Typed
License-File: LICENSE
License-File: AUTHORS.rst
Provides-Extra: dev
Requires-Dist: coverage (==5.5) ; extra == 'dev'
Requires-Dist: flake8 (==3.9.2) ; extra == 'dev'
Requires-Dist: mypy (==0.910) ; extra == 'dev'
Requires-Dist: sphinx (==5.0.2) ; extra == 'dev'
Requires-Dist: sphinxcontrib-httpdomain (==1.8.0) ; extra == 'dev'
Requires-Dist: sphinx-autodoc-typehints (==1.18.3) ; extra == 'dev'
Requires-Dist: sphinx-material (==0.0.35) ; extra == 'dev'
Requires-Dist: tox (==3.24.1) ; extra == 'dev'
Requires-Dist: yapf (==0.31.0) ; extra == 'dev'
Provides-Extra: test
Requires-Dist: coverage (==5.5) ; extra == 'test'
